spatstat_interface/__init__.py
spatstat_interface/interface.py
spatstat_interface/utils.py
spatstat_interface-1.0.1.dist-info/LICENSE
spatstat_interface-1.0.1.dist-info/WHEEL
spatstat_interface-1.0.1.dist-info/METADATA
spatstat_interface-1.0.1.dist-info/RECORD
