Metadata-Version: 2.1
Name: spatstat-interface
Version: 1.0.1
Summary: Simple Python interface with the spatstat R package using rpy2
Home-page: https://github.com/For-a-few-DPPs-more/spatstat-interface
License: MIT
Keywords: spatial statistics,point processes,python,R,spatstat
Author: Guillaume Gautier
Author-email: guillaume.gga@gmail.com
Maintainer: Guillaume Gautier
Maintainer-email: guillaume.gga@gmail.com
Requires-Python: >=3.7.1,<4.0.0
Classifier: Development Status :: 4 - Beta
Classifier: Intended Audience :: Science/Research
Classifier: License :: OSI Approved :: MIT License
Classifier: Programming Language :: Python :: 3
Classifier: Programming Language :: Python :: 3.8
Classifier: Programming Language :: Python :: 3.9
Classifier: Programming Language :: Python :: 3.10
Classifier: Programming Language :: Python :: 3.11
Classifier: Programming Language :: Python :: 3.7
Classifier: Programming Language :: Python :: 3.8
Classifier: Programming Language :: Python :: 3.9
Classifier: Programming Language :: R
Classifier: Topic :: Scientific/Engineering :: Mathematics
Classifier: Topic :: Software Development :: Libraries :: Python Modules
Provides-Extra: notebook
Requires-Dist: jupyter (>=1.0.0,<2.0.0) ; extra == "notebook"
Requires-Dist: matplotlib (>=3.5.2,<4.0.0) ; extra == "notebook"
Requires-Dist: numpy (>=1.20.3,<2.0.0) ; extra == "notebook"
Requires-Dist: pandas (>=1.2.4,<2.0.0)
Requires-Dist: rpy2 (>=3.4.5,<4.0.0)
Project-URL: Documentation, https://github.com/For-a-few-DPPs-more/spatstat-interface
Project-URL: Repository, https://github.com/For-a-few-DPPs-more/spatstat-interface
